{
  "kind": "collectionType",
  "collectionName": "services",
  "info": {
    "name": "Service",
    "description": ""
  },
  "options": {
    "increments": true,
    "timestamps": true,
    "draftAndPublish": false
  },
  "attributes": {
    "title": {
      "type": "string",
      "required": true
    },
    "slug": {
      "type": "uid",
      "targetField": "title",
      "required": true
    },
    "description": {
      "type": "text",
      "required": true
    },
    "cover": {
      "type": "component",
      "repeatable": false,
      "component": "page.photo",
      "required": true
    }
  }
}
